mask_divide/__init__.py
mask_divide/divide.py
mask_divide-1.0.0.dist-info/METADATA
mask_divide-1.0.0.dist-info/WHEEL
mask_divide-1.0.0.dist-info/entry_points.txt
mask_divide-1.0.0.dist-info/top_level.txt
mask_divide-1.0.0.dist-info/RECORD
