Metadata-Version: 2.1
Name: mask_divide
Version: 1.0.0
Summary: divide func added
Author-email: GITSangWoo <dogcenta@gmail.com>
License: MIT
Requires-Python: >=3.8
